<?xml version="1.0" encoding="UTF-8"?>

<!-- generated on 2023-02-01 16:31:03 by Eclipse SUMO sumo Version 1.10.0
<configuration xmlns:xsi="http://www.w3.org/2001/XMLSchema-instance" xsi:noNamespaceSchemaLocation="http://sumo.dlr.de/xsd/sumoConfiguration.xsd">

    <input>
        <net-file value="./input/Veberod_intersection_pedestrian.net.xml"/>
        <route-files value="./input/Veberod_intersection_pedestrian.rou.xml,./input/Veberod_intersection_pedestrian.trip.xml"/>
        <additional-files value="./input/Veberod_intersection_pedestrian.add.xml"/>
    </input>

    <output>
        <fcd-output value="./output/veberod-fcd.xml"/>
        <fcd-output.geo value="true"/>
    </output>

    <time>
        <begin value="0"/>
        <end value="3600"/>
        <step-length value="1"/>
    </time>

    <report>
        <no-warnings value="true"/>
        <no-step-log value="true"/>
    </report>

    <traci_server>
        <remote-port value="54199"/>
    </traci_server>

    <gui_only>
        <gui-settings-file value="./input/viewsettings.xml"/>
        <tracker-interval value="1"/>
    </gui_only>

</configuration>
-->

<detector xmlns:xsi="http://www.w3.org/2001/XMLSchema-instance" xsi:noNamespaceSchemaLocation="http://sumo.dlr.de/xsd/det_e1_file.xsd">
    <interval begin="0.00" end="300.00" id="det_13_0" nVehContrib="39" flow="468.00" occupancy="10.28" speed="7.04" harmonicMeanSpeed="6.32" length="5.00" nVehEntered="39"/>
    <interval begin="300.00" end="600.00" id="det_13_0" nVehContrib="40" flow="480.00" occupancy="11.01" speed="6.78" harmonicMeanSpeed="6.06" length="5.00" nVehEntered="40"/>
    <interval begin="600.00" end="900.00" id="det_13_0" nVehContrib="57" flow="684.00" occupancy="14.56" speed="7.17" harmonicMeanSpeed="6.52" length="5.00" nVehEntered="57"/>
    <interval begin="900.00" end="1200.00" id="det_13_0" nVehContrib="48" flow="576.00" occupancy="12.48" speed="7.11" harmonicMeanSpeed="6.41" length="5.00" nVehEntered="48"/>
    <interval begin="1200.00" end="1500.00" id="det_13_0" nVehContrib="47" flow="564.00" occupancy="12.63" speed="6.82" harmonicMeanSpeed="6.20" length="5.00" nVehEntered="47"/>
    <interval begin="1500.00" end="1800.00" id="det_13_0" nVehContrib="51" flow="612.00" occupancy="13.54" speed="7.01" harmonicMeanSpeed="6.28" length="5.00" nVehEntered="51"/>
    <interval begin="1800.00" end="2100.00" id="det_13_0" nVehContrib="65" flow="780.00" occupancy="17.20" speed="6.96" harmonicMeanSpeed="6.30" length="5.00" nVehEntered="65"/>
    <interval begin="2100.00" end="2400.00" id="det_13_0" nVehContrib="62" flow="744.00" occupancy="16.33" speed="6.89" harmonicMeanSpeed="6.33" length="5.00" nVehEntered="62"/>
    <interval begin="2400.00" end="2700.00" id="det_13_0" nVehContrib="39" flow="468.00" occupancy="10.23" speed="7.11" harmonicMeanSpeed="6.36" length="5.00" nVehEntered="39"/>
    <interval begin="2700.00" end="3000.00" id="det_13_0" nVehContrib="38" flow="456.00" occupancy="10.61" speed="6.64" harmonicMeanSpeed="5.97" length="5.00" nVehEntered="38"/>
    <interval begin="3000.00" end="3300.00" id="det_13_0" nVehContrib="60" flow="720.00" occupancy="15.84" speed="7.01" harmonicMeanSpeed="6.31" length="5.00" nVehEntered="60"/>
    <interval begin="3300.00" end="3600.00" id="det_13_0" nVehContrib="48" flow="576.00" occupancy="12.52" speed="7.07" harmonicMeanSpeed="6.39" length="5.00" nVehEntered="48"/>
    <interval begin="3600.00" end="3900.00" id="det_13_0" nVehContrib="56" flow="672.00" occupancy="13.71" speed="7.57" harmonicMeanSpeed="6.81" length="5.00" nVehEntered="56"/>
    <interval begin="3900.00" end="4200.00" id="det_13_0" nVehContrib="49" flow="588.00" occupancy="13.07" speed="7.01" harmonicMeanSpeed="6.25" length="5.00" nVehEntered="49"/>
    <interval begin="4200.00" end="4500.00" id="det_13_0" nVehContrib="52" flow="624.00" occupancy="13.34" speed="7.15" harmonicMeanSpeed="6.49" length="5.00" nVehEntered="52"/>
    <interval begin="4500.00" end="4800.00" id="det_13_0" nVehContrib="42" flow="504.00" occupancy="11.56" speed="6.70" harmonicMeanSpeed="6.06" length="5.00" nVehEntered="42"/>
    <interval begin="4800.00" end="5100.00" id="det_13_0" nVehContrib="44" flow="528.00" occupancy="11.78" speed="7.09" harmonicMeanSpeed="6.33" length="5.00" nVehEntered="45"/>
    <interval begin="5100.00" end="5400.00" id="det_13_0" nVehContrib="58" flow="696.00" occupancy="14.72" speed="7.15" harmonicMeanSpeed="6.48" length="5.00" nVehEntered="57"/>
    <interval begin="5400.00" end="5700.00" id="det_13_0" nVehContrib="57" flow="684.00" occupancy="14.94" speed="7.09" harmonicMeanSpeed="6.36" length="5.00" nVehEntered="57"/>
    <interval begin="5700.00" end="6000.00" id="det_13_0" nVehContrib="52" flow="624.00" occupancy="13.77" speed="6.92" harmonicMeanSpeed="6.29" length="5.00" nVehEntered="52"/>
    <interval begin="6000.00" end="6300.00" id="det_13_0" nVehContrib="43" flow="516.00" occupancy="11.55" speed="6.85" harmonicMeanSpeed="6.21" length="5.00" nVehEntered="43"/>
    <interval begin="6300.00" end="6600.00" id="det_13_0" nVehContrib="39" flow="468.00" occupancy="11.13" speed="6.47" harmonicMeanSpeed="5.84" length="5.00" nVehEntered="39"/>
    <interval begin="6600.00" end="6900.00" id="det_13_0" nVehContrib="57" flow="684.00" occupancy="14.18" speed="7.34" harmonicMeanSpeed="6.70" length="5.00" nVehEntered="57"/>
    <interval begin="6900.00" end="7200.00" id="det_13_0" nVehContrib="53" flow="636.00" occupancy="13.86" speed="7.00" harmonicMeanSpeed="6.37" length="5.00" nVehEntered="53"/>
    <interval begin="7200.00" end="7500.00" id="det_13_0" nVehContrib="59" flow="708.00" occupancy="15.56" speed="6.99" harmonicMeanSpeed="6.32" length="5.00" nVehEntered="59"/>
    <interval begin="7500.00" end="7800.00" id="det_13_0" nVehContrib="60" flow="720.00" occupancy="16.25" speed="6.96" harmonicMeanSpeed="6.21" length="5.00" nVehEntered="61"/>
    <interval begin="7800.00" end="8100.00" id="det_13_0" nVehContrib="38" flow="456.00" occupancy="9.57" speed="7.11" harmonicMeanSpeed="6.51" length="5.00" nVehEntered="37"/>
    <interval begin="8100.00" end="8400.00" id="det_13_0" nVehContrib="61" flow="732.00" occupancy="15.84" speed="7.13" harmonicMeanSpeed="6.42" length="5.00" nVehEntered="61"/>
    <interval begin="8400.00" end="8700.00" id="det_13_0" nVehContrib="43" flow="516.00" occupancy="11.32" speed="7.07" harmonicMeanSpeed="6.33" length="5.00" nVehEntered="43"/>
    <interval begin="8700.00" end="9000.00" id="det_13_0" nVehContrib="59" flow="708.00" occupancy="15.27" speed="7.01" harmonicMeanSpeed="6.44" length="5.00" nVehEntered="59"/>
    <interval begin="9000.00" end="9300.00" id="det_13_0" nVehContrib="48" flow="576.00" occupancy="12.55" speed="7.02" harmonicMeanSpeed="6.37" length="5.00" nVehEntered="48"/>
    <interval begin="9300.00" end="9600.00" id="det_13_0" nVehContrib="49" flow="588.00" occupancy="12.17" speed="7.43" harmonicMeanSpeed="6.71" length="5.00" nVehEntered="49"/>
    <interval begin="9600.00" end="9900.00" id="det_13_0" nVehContrib="61" flow="732.00" occupancy="15.47" speed="7.23" harmonicMeanSpeed="6.57" length="5.00" nVehEntered="61"/>
    <interval begin="9900.00" end="10200.00" id="det_13_0" nVehContrib="44" flow="528.00" occupancy="11.68" speed="6.97" harmonicMeanSpeed="6.28" length="5.00" nVehEntered="44"/>
    <interval begin="10200.00" end="10500.00" id="det_13_0" nVehContrib="58" flow="696.00" occupancy="15.46" speed="6.98" harmonicMeanSpeed="6.25" length="5.00" nVehEntered="58"/>
    <interval begin="10500.00" end="10800.00" id="det_13_0" nVehContrib="44" flow="528.00" occupancy="11.57" speed="7.15" harmonicMeanSpeed="6.34" length="5.00" nVehEntered="44"/>
    <interval begin="10800.00" end="11100.00" id="det_13_0" nVehContrib="53" flow="636.00" occupancy="14.53" speed="6.60" harmonicMeanSpeed="6.08" length="5.00" nVehEntered="53"/>
    <interval begin="11100.00" end="11400.00" id="det_13_0" nVehContrib="49" flow="588.00" occupancy="13.00" speed="6.93" harmonicMeanSpeed="6.28" length="5.00" nVehEntered="49"/>
    <interval begin="11400.00" end="11700.00" id="det_13_0" nVehContrib="57" flow="684.00" occupancy="15.53" speed="6.83" harmonicMeanSpeed="6.12" length="5.00" nVehEntered="57"/>
    <interval begin="11700.00" end="12000.00" id="det_13_0" nVehContrib="39" flow="468.00" occupancy="10.30" speed="7.07" harmonicMeanSpeed="6.31" length="5.00" nVehEntered="39"/>
    <interval begin="12000.00" end="12300.00" id="det_13_0" nVehContrib="53" flow="636.00" occupancy="14.85" speed="6.52" harmonicMeanSpeed="5.95" length="5.00" nVehEntered="53"/>
    <interval begin="12300.00" end="12600.00" id="det_13_0" nVehContrib="57" flow="684.00" occupancy="15.39" speed="6.91" harmonicMeanSpeed="6.17" length="5.00" nVehEntered="57"/>
    <interval begin="12600.00" end="12900.00" id="det_13_0" nVehContrib="61" flow="732.00" occupancy="16.47" speed="6.96" harmonicMeanSpeed="6.27" length="5.00" nVehEntered="62"/>
    <interval begin="12900.00" end="13200.00" id="det_13_0" nVehContrib="56" flow="672.00" occupancy="14.17" speed="7.20" harmonicMeanSpeed="6.47" length="5.00" nVehEntered="55"/>
    <interval begin="13200.00" end="13500.00" id="det_13_0" nVehContrib="38" flow="456.00" occupancy="10.31" speed="6.82" harmonicMeanSpeed="6.14" length="5.00" nVehEntered="38"/>
    <interval begin="13500.00" end="13800.00" id="det_13_0" nVehContrib="54" flow="648.00" occupancy="14.34" speed="6.98" harmonicMeanSpeed="6.28" length="5.00" nVehEntered="54"/>
    <interval begin="13800.00" end="14100.00" id="det_13_0" nVehContrib="45" flow="540.00" occupancy="11.97" speed="7.08" harmonicMeanSpeed="6.27" length="5.00" nVehEntered="45"/>
    <interval begin="14100.00" end="14400.00" id="det_13_0" nVehContrib="67" flow="804.00" occupancy="18.48" speed="6.63" harmonicMeanSpeed="6.04" length="5.00" nVehEntered="67"/>
    <interval begin="14400.00" end="14700.00" id="det_13_0" nVehContrib="45" flow="540.00" occupancy="12.83" speed="6.58" harmonicMeanSpeed="5.84" length="5.00" nVehEntered="45"/>
    <interval begin="14700.00" end="15000.00" id="det_13_0" nVehContrib="53" flow="636.00" occupancy="14.98" speed="6.62" harmonicMeanSpeed="6.01" length="5.00" nVehEntered="54"/>
    <interval begin="15000.00" end="15300.00" id="det_13_0" nVehContrib="47" flow="564.00" occupancy="11.96" speed="7.09" harmonicMeanSpeed="6.40" length="5.00" nVehEntered="46"/>
    <interval begin="15300.00" end="15600.00" id="det_13_0" nVehContrib="53" flow="636.00" occupancy="14.41" speed="6.70" harmonicMeanSpeed="6.13" length="5.00" nVehEntered="53"/>
    <interval begin="15600.00" end="15900.00" id="det_13_0" nVehContrib="57" flow="684.00" occupancy="15.01" speed="6.95" harmonicMeanSpeed="6.39" length="5.00" nVehEntered="58"/>
    <interval begin="15900.00" end="16200.00" id="det_13_0" nVehContrib="54" flow="648.00" occupancy="14.12" speed="6.95" harmonicMeanSpeed="6.30" length="5.00" nVehEntered="53"/>
    <interval begin="16200.00" end="16500.00" id="det_13_0" nVehContrib="40" flow="480.00" occupancy="10.72" speed="6.85" harmonicMeanSpeed="6.22" length="5.00" nVehEntered="40"/>
    <interval begin="16500.00" end="16800.00" id="det_13_0" nVehContrib="38" flow="456.00" occupancy="10.35" speed="6.76" harmonicMeanSpeed="6.12" length="5.00" nVehEntered="38"/>
    <interval begin="16800.00" end="17100.00" id="det_13_0" nVehContrib="56" flow="672.00" occupancy="14.67" speed="7.02" harmonicMeanSpeed="6.36" length="5.00" nVehEntered="56"/>
    <interval begin="17100.00" end="17400.00" id="det_13_0" nVehContrib="52" flow="624.00" occupancy="13.81" speed="6.97" harmonicMeanSpeed="6.28" length="5.00" nVehEntered="52"/>
    <interval begin="17400.00" end="17700.00" id="det_13_0" nVehContrib="49" flow="588.00" occupancy="13.20" speed="6.93" harmonicMeanSpeed="6.19" length="5.00" nVehEntered="49"/>
    <interval begin="17700.00" end="18000.00" id="det_13_0" nVehContrib="52" flow="624.00" occupancy="13.79" speed="7.01" harmonicMeanSpeed="6.28" length="5.00" nVehEntered="52"/>
    <interval begin="18000.00" end="18300.00" id="det_13_0" nVehContrib="47" flow="564.00" occupancy="12.63" speed="6.86" harmonicMeanSpeed="6.20" length="5.00" nVehEntered="47"/>
    <interval begin="18300.00" end="18600.00" id="det_13_0" nVehContrib="45" flow="540.00" occupancy="12.41" speed="6.83" harmonicMeanSpeed="6.04" length="5.00" nVehEntered="45"/>
    <interval begin="18600.00" end="18900.00" id="det_13_0" nVehContrib="42" flow="504.00" occupancy="11.82" speed="6.54" harmonicMeanSpeed="5.92" length="5.00" nVehEntered="42"/>
    <interval begin="18900.00" end="19200.00" id="det_13_0" nVehContrib="56" flow="672.00" occupancy="15.09" speed="6.85" harmonicMeanSpeed="6.19" length="5.00" nVehEntered="56"/>
    <interval begin="19200.00" end="19500.00" id="det_13_0" nVehContrib="42" flow="504.00" occupancy="11.75" speed="6.66" harmonicMeanSpeed="5.99" length="5.00" nVehEntered="43"/>
    <interval begin="19500.00" end="19800.00" id="det_13_0" nVehContrib="45" flow="540.00" occupancy="12.67" speed="6.51" harmonicMeanSpeed="5.89" length="5.00" nVehEntered="44"/>
    <interval begin="19800.00" end="20100.00" id="det_13_0" nVehContrib="50" flow="600.00" occupancy="13.27" speed="7.01" harmonicMeanSpeed="6.28" length="5.00" nVehEntered="50"/>
    <interval begin="20100.00" end="20400.00" id="det_13_0" nVehContrib="43" flow="516.00" occupancy="11.37" speed="6.93" harmonicMeanSpeed="6.31" length="5.00" nVehEntered="43"/>
    <interval begin="20400.00" end="20700.00" id="det_13_0" nVehContrib="56" flow="672.00" occupancy="15.18" speed="6.81" harmonicMeanSpeed="6.15" length="5.00" nVehEntered="56"/>
    <interval begin="20700.00" end="21000.00" id="det_13_0" nVehContrib="56" flow="672.00" occupancy="14.75" speed="7.05" harmonicMeanSpeed="6.33" length="5.00" nVehEntered="56"/>
    <interval begin="21000.00" end="21300.00" id="det_13_0" nVehContrib="37" flow="444.00" occupancy="10.43" speed="6.62" harmonicMeanSpeed="5.91" length="5.00" nVehEntered="37"/>
    <interval begin="21300.00" end="21600.00" id="det_13_0" nVehContrib="54" flow="648.00" occupancy="14.55" speed="6.91" harmonicMeanSpeed="6.18" length="5.00" nVehEntered="54"/>
    <interval begin="21600.00" end="21900.00" id="det_13_0" nVehContrib="56" flow="672.00" occupancy="14.99" speed="6.97" harmonicMeanSpeed="6.23" length="5.00" nVehEntered="56"/>
    <interval begin="21900.00" end="22200.00" id="det_13_0" nVehContrib="46" flow="552.00" occupancy="12.78" speed="6.67" harmonicMeanSpeed="6.00" length="5.00" nVehEntered="46"/>
    <interval begin="22200.00" end="22500.00" id="det_13_0" nVehContrib="56" flow="672.00" occupancy="14.87" speed="7.12" harmonicMeanSpeed="6.28" length="5.00" nVehEntered="56"/>
    <interval begin="22500.00" end="22800.00" id="det_13_0" nVehContrib="40" flow="480.00" occupancy="12.05" speed="6.09" harmonicMeanSpeed="5.53" length="5.00" nVehEntered="40"/>
    <interval begin="22800.00" end="23100.00" id="det_13_0" nVehContrib="50" flow="600.00" occupancy="13.72" speed="6.83" harmonicMeanSpeed="6.07" length="5.00" nVehEntered="50"/>
    <interval begin="23100.00" end="23400.00" id="det_13_0" nVehContrib="51" flow="612.00" occupancy="14.52" speed="6.54" harmonicMeanSpeed="5.85" length="5.00" nVehEntered="51"/>
    <interval begin="23400.00" end="23700.00" id="det_13_0" nVehContrib="60" flow="720.00" occupancy="15.74" speed="7.01" harmonicMeanSpeed="6.35" length="5.00" nVehEntered="60"/>
    <interval begin="23700.00" end="24000.00" id="det_13_0" nVehContrib="58" flow="696.00" occupancy="16.03" speed="6.67" harmonicMeanSpeed="6.03" length="5.00" nVehEntered="58"/>
    <interval begin="24000.00" end="24300.00" id="det_13_0" nVehContrib="52" flow="624.00" occupancy="15.38" speed="6.43" harmonicMeanSpeed="5.63" length="5.00" nVehEntered="52"/>
    <interval begin="24300.00" end="24600.00" id="det_13_0" nVehContrib="57" flow="684.00" occupancy="15.94" speed="6.71" harmonicMeanSpeed="5.96" length="5.00" nVehEntered="57"/>
    <interval begin="24600.00" end="24900.00" id="det_13_0" nVehContrib="56" flow="672.00" occupancy="15.19" speed="6.86" harmonicMeanSpeed="6.15" length="5.00" nVehEntered="56"/>
    <interval begin="24900.00" end="25200.00" id="det_13_0" nVehContrib="49" flow="588.00" occupancy="14.05" speed="6.51" harmonicMeanSpeed="5.81" length="5.00" nVehEntered="49"/>
    <interval begin="25200.00" end="25500.00" id="det_13_0" nVehContrib="50" flow="600.00" occupancy="14.18" speed="6.53" harmonicMeanSpeed="5.88" length="5.00" nVehEntered="50"/>
    <interval begin="25500.00" end="25800.00" id="det_13_0" nVehContrib="40" flow="480.00" occupancy="11.47" speed="6.52" harmonicMeanSpeed="5.81" length="5.00" nVehEntered="40"/>
    <interval begin="25800.00" end="26100.00" id="det_13_0" nVehContrib="54" flow="648.00" occupancy="15.60" speed="6.41" harmonicMeanSpeed="5.77" length="5.00" nVehEntered="54"/>
    <interval begin="26100.00" end="26400.00" id="det_13_0" nVehContrib="51" flow="612.00" occupancy="14.67" speed="6.46" harmonicMeanSpeed="5.79" length="5.00" nVehEntered="51"/>
    <interval begin="26400.00" end="26700.00" id="det_13_0" nVehContrib="51" flow="612.00" occupancy="14.88" speed="6.48" harmonicMeanSpeed="5.71" length="5.00" nVehEntered="51"/>
    <interval begin="26700.00" end="27000.00" id="det_13_0" nVehContrib="60" flow="720.00" occupancy="17.71" speed="6.26" harmonicMeanSpeed="5.65" length="5.00" nVehEntered="60"/>
    <interval begin="27000.00" end="27300.00" id="det_13_0" nVehContrib="40" flow="480.00" occupancy="11.38" speed="6.68